wzy_bt_print/__init__.py
wzy_bt_print-0.1.2.dist-info/LICENSE
wzy_bt_print-0.1.2.dist-info/METADATA
wzy_bt_print-0.1.2.dist-info/WHEEL
wzy_bt_print-0.1.2.dist-info/top_level.txt
wzy_bt_print-0.1.2.dist-info/RECORD
