Metadata-Version: 2.1
Name: wzy_bt_print
Version: 0.1.2
Summary: Binary Tree Printout
Home-page: https://github.com/Dr-WangZhiyuan/wzy_bt_print
Author: Dr. Zhiyuan Wang
Author-email: wang1399@e.ntu.edu.sg
License: MIT
Platform: UNKNOWN
Classifier: Programming Language :: Python :: 3
Classifier: License :: OSI Approved :: MIT License
License-File: LICENSE
